dotenvit/__init__.py
dotenvit-0.1.0.dist-info/METADATA
dotenvit-0.1.0.dist-info/WHEEL
dotenvit-0.1.0.dist-info/top_level.txt
dotenvit-0.1.0.dist-info/RECORD
