Metadata-Version: 2.1
Name: dotenvit
Version: 0.1.0
Summary: A simple key store .env manager damnit
Home-page: UNKNOWN
Author: plusleft
Author-email: UNKNOWN
License: UNKNOWN
Platform: UNKNOWN
